pdbear/__init__.py
pdbear-0.1.dist-info/METADATA
pdbear-0.1.dist-info/RECORD
pdbear-0.1.dist-info/WHEEL
pdbear-0.1.dist-info/top_level.txt
